pyBioTools/Alignment.py
pyBioTools/Annotation.py
pyBioTools/Fasta.py
pyBioTools/Fastq.py
pyBioTools/__init__.py
pyBioTools/__main__.py
pyBioTools/common.py
pyBioTools-0.1.0.0.dist-info/METADATA
pyBioTools-0.1.0.0.dist-info/RECORD
pyBioTools-0.1.0.0.dist-info/WHEEL
pyBioTools-0.1.0.0.dist-info/entry_points.txt
pyBioTools-0.1.0.0.dist-info/top_level.txt
