Metadata-Version: 2.1
Name: pyBioTools
Version: 0.1.0.0
Summary: pyBioTools is a collection of tools to manipulate biological sequences
Home-page: https://github.com/a-slide/pyBioTools
Author: Adrien Leger
Author-email: aleg@ebi.ac.uk
License: GPLv3
Platform: UNKNOWN
Classifier: Development Status :: 3 - Alpha
Classifier: Intended Audience :: Science/Research
Classifier: Topic :: Scientific/Engineering :: Bio-Informatics
Classifier: License :: OSI Approved :: GNU General Public License v3 (GPLv3)
Classifier: Programming Language :: Python :: 3
Requires-Python: >=3.5
Requires-Dist: tqdm (>=4.32.1)
Requires-Dist: numpy (>=1.16.4)
Requires-Dist: pysam (>=0.15.2)
Requires-Dist: pandas (>=0.24.2)
